{
  "generator-jhipster": {
    "promptValues": {
      "packageName": "com.kidole.sport",
      "nativeLanguage": "fr"
    },
    "jhipsterVersion": "6.6.0",
    "applicationType": "monolith",
    "baseName": "kidole",
    "packageName": "com.kidole.sport",
    "packageFolder": "com/kidole/sport",
    "serverPort": "8080",
    "authenticationType": "jwt",
    "cacheProvider": "ehcache",
    "enableHibernateCache": true,
    "websocket": false,
    "databaseType": "sql",
    "devDatabaseType": "h2Disk",
    "prodDatabaseType": "mysql",
    "searchEngine": "elasticsearch",
    "messageBroker": false,
    "serviceDiscoveryType": false,
    "buildTool": "maven",
    "enableSwaggerCodegen": false,
    "jwtSecretKey": "ZDRiNGU5ZjZiNDhkN2VjZGVlOGY4YWJjOTkxZTJlZTJlNjE4ZWM3ZTJhMzAxN2M3OTQ1NTYzMjQ0Nzc0N2ZiZTQ3OWFlOWU3Yjc3NzYzYzIwYjQ5YWM0MTIzODllMGJhMjYwMGQ5NjMzZGJjYmI1NWZlMGNlYmQwYmNhMDI1MjY=",
    "embeddableLaunchScript": false,
    "useSass": true,
    "clientPackageManager": "npm",
    "clientFramework": "angularX",
    "clientTheme": "simplex",
    "clientThemeVariant": "light",
    "creationTimestamp": 1580825244177,
    "testFrameworks": ["protractor"],
    "jhiPrefix": "jhi",
    "entitySuffix": "",
    "dtoSuffix": "DTO",
    "otherModules": [],
    "enableTranslation": true,
    "nativeLanguage": "fr",
    "languages": ["fr", "en"],
    "blueprints": []
  }
}
